{
    "id":  "containment_bay_p1t6_extreme",
    "name":  "兵器隔離倉P1T6 (殲殛戰) - 祖爾宛",
    "nameEn":  "Containment Bay P1T6 (Extreme) - Zurvan",
    "expansion":  "3.x 蒼穹的禁城 (Heavensward)",
    "type":  "trial",
    "playerCount":  8,
    "iLvlSync":  null,
    "jobLevelSync":  60,
    "highEnd":  true,
    "quality":  "excellent",
    "mnemonic":  [
                     "1）Sophia：Arm\u0027s Length",
                     "2）Thunder III and two copy Aero III / Thunder II and three copy Aero III",
                     "3）Horizontal Kenoma"
                 ],
    "notes":  "3.x 蒼穹的禁城 (Heavensward)[0]) other (Lv 60)。",
    "bosses":  [
                   {
                       "phases":  [
                                      {
                                          "name":  "主戰",
                                          "mechanics":  [
                                                            {
                                                                "description":  "Surecast.；依預兆走位處理。",
                                                                "name":  "Arm\u0027s Length 臂",
                                                                "tips":  [
                                                                             "看 telegraph 移動"
                                                                         ],
                                                                "type":  "other"
                                                            },
                                                            {
                                                                "description":  "依預兆走位處理。",
                                                                "name":  "Thunder III and two copy Aero III 疾風 III",
                                                                "tips":  [
                                                                             "看 telegraph 移動"
                                                                         ],
                                                                "type":  "other"
                                                            },
                                                            {
                                                                "description":  "依預兆走位處理。",
                                                                "name":  "Thunder II and three copy Aero III 疾風 III",
                                                                "tips":  [
                                                                             "看 telegraph 移動"
                                                                         ],
                                                                "type":  "other"
                                                            },
                                                            {
                                                                "description":  "which can only be cured by defeating all three Demiurges.；依預兆走位處理。",
                                                                "name":  "Eternal Doom 末日",
                                                                "tips":  [
                                                                             "看 telegraph 移動"
                                                                         ],
                                                                "type":  "other"
                                                            },
                                                            {
                                                                "description":  "for 20 seconds.；依預兆走位處理。",
                                                                "name":  "Zombification 招式",
                                                                "tips":  [
                                                                             "看 telegraph 移動"
                                                                         ],
                                                                "type":  "other"
                                                            },
                                                            {
                                                                "description":  "Gain\u0027s a .；依預兆走位處理。",
                                                                "name":  "Vertical Kenoma 垂直空無",
                                                                "tips":  [
                                                                             "看 telegraph 移動"
                                                                         ],
                                                                "type":  "other"
                                                            },
                                                            {
                                                                "description":  "to its front and back for 6 seconds.；依預兆走位處理。",
                                                                "name":  "Directional Parry 招式",
                                                                "tips":  [
                                                                             "看 telegraph 移動"
                                                                         ],
                                                                "type":  "other"
                                                            },
                                                            {
                                                                "description":  "The same as Vertical Kenoma but instead protects the sides.；依預兆走位處理。",
                                                                "name":  "Horizontal Kenoma 水平空無",
                                                                "tips":  [
                                                                             "看 telegraph 移動"
                                                                         ],
                                                                "type":  "other"
                                                            }
                                                        ]
                                      }
                                  ],
                       "name":  "索菲娅",
                       "nameEn":  "Sophia",
                       "mnemonic":  [
                                        "Arm\u0027s Length",
                                        "Thunder III and two copy Aero III",
                                        "Thunder II and three copy Aero III"
                                    ]
                   }
               ]
}