{
  "id": "navel_extreme",
  "name": "泰坦殲殛戰",
  "nameEn": "The Navel (Extreme)",
  "expansion": "2.x 重生之境 (A Realm Reborn)",
  "type": "trial",
  "playerCount": 8,
  "iLvlSync": null,
  "jobLevelSync": 50,
  "highEnd": false,
  "quality": "needs-update",
  "mnemonic": [
    "泰坦絕境戰 (Ex)",
    "場地圓形，邊緣會崩裂",
    "Geocrush 跳擊退 → 靠邊但別站崩裂處",
    "Bomb：DPS 打掉避免擊退",
    "Heart of the Mountain：Boss 心臟，DPS check"
  ],
  "notes": "Primal 泰坦的絕境戰版本，著名 DPS check 與場地崩裂機制。⚠️ AI 預填內容。",
  "bosses": [
    {
      "name": "泰坦 (Ex)",
      "nameEn": "Titan",
      "mnemonic": [
        "Geocrush 跳擊退（場邊但避開崩裂）",
        "Landslide 直線擊退",
        "Weight of the Land 散開",
        "Bomb：DPS 打掉避免擊退",
        "Heart of the Mountain：DPS check"
      ],
      "phases": [
        {
          "name": "主戰",
          "mechanics": [
            {
              "name": "Geocrush + 場地崩裂",
              "type": "raidwide",
              "description": "Boss 跳擊退，且場地邊緣會逐漸崩裂變小。",
              "tips": [
                "Geocrush 靠邊吃擊退",
                "但避開已崩裂的破洞",
                "後期場地越來越小"
              ]
            },
            {
              "name": "Landslide",
              "type": "aoe",
              "description": "前方直線 AoE 配擊退。",
              "tips": [
                "閃到線外",
                "若被擊退注意不要掉場"
              ]
            },
            {
              "name": "Bomb",
              "type": "other",
              "description": "場上出現炸彈，若不打掉會自爆造成擊退。",
              "tips": [
                "DPS 切換攻擊炸彈",
                "讓炸彈在安全位置爆炸"
              ]
            },
            {
              "name": "Heart of the Mountain（心臟）",
              "type": "other",
              "description": "Boss 召喚心臟，DPS check，需在時限內打爆。",
              "tips": [
                "DPS 全力打心臟",
                "心臟未打掉會召喚援軍或大幅增益 Boss"
              ]
            },
            {
              "name": "Weight of the Land",
              "type": "spread",
              "description": "腳下黃色圓圈，散開。",
              "tips": [
                "散開避免重疊"
              ]
            }
          ]
        }
      ]
    }
  ]
}
